feedback-0.1.post7.dist-info/METADATA
feedback-0.1.post7.dist-info/WHEEL
feedback-0.1.post7.dist-info/metadata.json
feedback-0.1.post7.dist-info/RECORD
feedback-0.1.post7.dist-info/top_level.txt
feedback-0.1.post7.dist-info/DESCRIPTION.rst
feedback-0.1.post7.dist-info/pbr.json
feedback/render.py
feedback/__init__.py
